etcetera/__init__.py
etcetera/api.py
etcetera/cli.py
etcetera/config.py
etcetera/dataset.py
etcetera/engine.py
etcetera/repo.py
etcetera/impl/mock.py
etcetera/impl/s3.py
etcetera-0.0.12.dist-info/METADATA
etcetera-0.0.12.dist-info/WHEEL
etcetera-0.0.12.dist-info/entry_points.txt
etcetera-0.0.12.dist-info/top_level.txt
etcetera-0.0.12.dist-info/RECORD
