Metadata-Version: 2.1
Name: etcetera
Version: 0.0.12
Summary: Sharing datasets via cloud storage
Home-page: http://github.com/pgmmpk/etcetera
Author: Mike Kroutikov
Author-email: pgmmpk@gmail.com
License: MIT
Platform: UNKNOWN
Classifier: Environment :: Web Environment
Classifier: Intended Audience :: Developers
Classifier: License :: OSI Approved :: MIT License
Classifier: Programming Language :: Python
Classifier: Programming Language :: Python :: 3
Requires-Python: >=3.6
Requires-Dist: toml
Provides-Extra: s3
Requires-Dist: boto3 ; extra == 's3'
